sysfsgpio/__init__.py
sysfsgpio/pin.py
sysfsgpio/utils.py
sysfsgpio/version.py
sysfsgpio/resources/gpio-exporter.service
sysfsgpio/resources/sysfsgpio.rules
trimarlib_sysfsgpio-0.2.1.dist-info/METADATA
trimarlib_sysfsgpio-0.2.1.dist-info/RECORD
trimarlib_sysfsgpio-0.2.1.dist-info/WHEEL
trimarlib_sysfsgpio-0.2.1.dist-info/entry_points.txt
trimarlib_sysfsgpio-0.2.1.dist-info/top_level.txt
