Metadata-Version: 2.1
Name: trimarlib-sysfsgpio
Version: 0.2.1
Summary: Sysfs GPIO utility
Home-page: https://dsl2.trimar.org/pythons-ll/sysfsgpiolib
Author: TRIMAR Developer
Author-email: developer@trimar.com.pl
License: UNKNOWN
Platform: UNKNOWN
Classifier: Programming Language :: Python :: 3
Classifier: License :: OSI Approved :: MIT License
Classifier: Operating System :: POSIX :: Linux
